django_postgres_copy-2.8.0.dist-info/licenses/LICENSE
postgres_copy/__init__.py
postgres_copy/copy_from.py
postgres_copy/copy_to.py
postgres_copy/managers.py
postgres_copy/psycopg_compat.py
django_postgres_copy-2.8.0.dist-info/METADATA
django_postgres_copy-2.8.0.dist-info/WHEEL
django_postgres_copy-2.8.0.dist-info/top_level.txt
django_postgres_copy-2.8.0.dist-info/RECORD
